Metadata-Version: 2.1
Name: Notes-utils061072023
Version: 1.0
Summary: Блокнот с заметками
Author: Yurii Khomich
Author-email: 123@gmail.com
